[
    {
        "Product Name": "Vòng từ tính: hút nam châm cực mạnh, chất liệu kim loại cao cấp, siêu mỏng",
        "Current Price": "1.000 ₫",
        "Original Price": "30.000 ₫",
        "Percent Badge": "-97%",
        "Amount Info": "Số lượng: 22",
        "Image": "https://cf.shopee.vn/file/vn-11134207-7ras8-mal36n9dihnc3a",
        "Original Link": "https://s.shopee.vn/7AalHfosyC",
        "Affiliate Link": "https://shorten.asia/k2Sehwjm",
        "Scraping Time": "29-05 Khung: 12:00"
    },
    {
        "Product Name": "Dụng cụ gỡ lưỡi câu và buộc lưỡi câu tiện lợi đi câu fishing",
        "Current Price": "1.000 ₫",
        "Original Price": "17.500 ₫",
        "Percent Badge": "-94%",
        "Amount Info": "Số lượng: 25",
        "Image": "https://cf.shopee.vn/file/vn-11134207-81ztc-mlvczzqtv4zpaa",
        "Original Link": "https://s.shopee.vn/70HL5MpWJB",
        "Affiliate Link": "https://shorten.asia/xxZdP8GJ",
        "Scraping Time": "29-05 Khung: 12:00"
    },
    {
        "Product Name": "Dầu Gội Nâu Trà Sữa Labene Dành Cho Tóc Nhuộm Nâu, Bổ Sung Tăng Độ Sáng Tươi Mới Màu Nhuộm",
        "Current Price": "29.000 ₫",
        "Original Price": "239.000 ₫",
        "Percent Badge": "-88%",
        "Amount Info": "Số lượng: 50",
        "Image": "https://cf.shopee.vn/file/vn-11134207-81ztc-moaulo4w7tal1a",
        "Original Link": "https://s.shopee.vn/6pxut3q9eA",
        "Affiliate Link": "https://shorten.asia/EfahTdtR",
        "Scraping Time": "29-05 Khung: 12:00"
    },
    {
        "Product Name": "Sách Đắc Nhân Tâm Và Quẳng Gánh Lo Đi Và Vui Sống - Dale Carnegie - Nguyễn Hiến Lê Dịch -(Khổ Nhỏ 10*15cm)",
        "Current Price": "9.000 ₫",
        "Original Price": "66.000 ₫",
        "Percent Badge": "-86%",
        "Amount Info": "Số lượng: 20",
        "Image": "https://cf.shopee.vn/file/vn-11134207-7ras8-mc7lc7vasq8l38",
        "Original Link": "https://s.shopee.vn/6feUgkqmz9",
        "Affiliate Link": "https://shorten.asia/1bJDyyWZ",
        "Scraping Time": "29-05 Khung: 12:00"
    },
    {
        "Product Name": "Bao cao su Endless gân gai, nhiều gel bôi trơn - Hộp 01 bcs",
        "Current Price": "9.000 ₫",
        "Original Price": "60.000 ₫",
        "Percent Badge": "-85%",
        "Amount Info": "Số lượng: 25",
        "Image": "https://cf.shopee.vn/file/vn-11134207-81ztc-mojff44gd7nl2b",
        "Original Link": "https://s.shopee.vn/9ALpfLhGue",
        "Affiliate Link": "https://shorten.asia/cXpwqZh3",
        "Scraping Time": "29-05 Khung: 12:00"
    },
    {
        "Product Name": "Hộp thực phẩm trữ đông Hokkaido kháng khuẩn, nắp có đồng hồ ghi nhớ thời gian trữ đông Inochi Amazing Mall",
        "Current Price": "9.000 ₫",
        "Original Price": "51.000 ₫",
        "Percent Badge": "-82%",
        "Amount Info": "Số lượng: 14",
        "Image": "https://cf.shopee.vn/file/vn-11134207-7ras8-m4r6b8k3e4g7e5",
        "Original Link": "https://s.shopee.vn/902PT2huFd",
        "Affiliate Link": "https://shorten.asia/QSmZMPHP",
        "Scraping Time": "29-05 Khung: 12:00"
    },
    {
        "Product Name": "Combo 20 Móc Dán Tường Siêu Dính, Chất Liệu Inox 304 Chắc Chắn Chịu Lực Tốt, Treo Đồ Siêu Tiện Lợi",
        "Current Price": "9.000 ₫",
        "Original Price": "49.000 ₫",
        "Percent Badge": "-82%",
        "Amount Info": "Số lượng: 15",
        "Image": "https://cf.shopee.vn/file/vn-11134207-81ztc-mnxpqwjhdkw4df",
        "Original Link": "https://s.shopee.vn/8pizGjiXac",
        "Affiliate Link": "https://shorten.asia/8UCC2cZG",
        "Scraping Time": "29-05 Khung: 12:00"
    },
    {
        "Product Name": "[DEAL HOT] Ổ Cắm Điện Đa Năng DELI Chịu Tải 2500W Ổ Tam Giác Dây Dài 3-5m Cổng USB Chống Cháy Chống Giật",
        "Current Price": "44.000 ₫",
        "Original Price": "190.000 ₫",
        "Percent Badge": "-77%",
        "Amount Info": "Số lượng: 155",
        "Image": "https://cf.shopee.vn/file/vn-11134207-81ztc-mo80t94xdwqt71",
        "Original Link": "https://s.shopee.vn/8fPZ4QjAvb",
        "Affiliate Link": "https://shorten.asia/8d6GBM9p",
        "Scraping Time": "29-05 Khung: 12:00"
    },
    {
        "Product Name": "Nút chặn thoát nước bồn rửa mặt 2in1- Kèm bộ lọc rác ngăn tắc, thoát nước nhanh, dễ lắp đặt.",
        "Current Price": "9.000 ₫",
        "Original Price": "38.400 ₫",
        "Percent Badge": "-77%",
        "Amount Info": "Số lượng: 25",
        "Image": "https://cf.shopee.vn/file/vn-11134201-7ras8-m0tkkhdyedil69",
        "Original Link": "https://s.shopee.vn/8V68s7joGa",
        "Affiliate Link": "https://shorten.asia/1K1krCK6",
        "Scraping Time": "29-05 Khung: 12:00"
    },
    {
        "Product Name": "Sách - Bộ Sách Bé Có Làm Được Không?  - Bộ sách dành cho bé trên 1 tuổi - MCBooks Chính Hãng",
        "Current Price": "9.000 ₫",
        "Original Price": "39.000 ₫",
        "Percent Badge": "-77%",
        "Amount Info": "Số lượng: 10",
        "Image": "https://cf.shopee.vn/file/vn-11134207-7r98o-ly1pm4vd8qu1f6",
        "Original Link": "https://s.shopee.vn/8KmifokRbZ",
        "Affiliate Link": "https://shorten.asia/PdaxjwUK",
        "Scraping Time": "29-05 Khung: 12:00"
    },
    {
        "Product Name": "Ốp bảo vệ silicon 2 trong 1 hợp thời trang sáng tạo Tương thích cho IPhone 17 16 11 12 13 14 15 Pro Max Air 7Plus XR X XS Max 6 15 16 7 14 6s Plus Vỏ mềm điện thoại",
        "Current Price": "9.000 ₫",
        "Original Price": "39.998 ₫",
        "Percent Badge": "-77%",
        "Amount Info": "Số lượng: 24",
        "Image": "https://cf.shopee.vn/file/sg-11134201-82274-mhvi5mmvkt8jfb",
        "Original Link": "https://s.shopee.vn/8ATITVl4wY",
        "Affiliate Link": "https://shorten.asia/1BM6q3BT",
        "Scraping Time": "29-05 Khung: 12:00"
    },
    {
        "Product Name": "Lọ xay tiêu cầm tay thủy tinh và inox 304 cao cấp DandiHome tiện lợi",
        "Current Price": "29.000 ₫",
        "Original Price": "118.000 ₫",
        "Percent Badge": "-75%",
        "Amount Info": "Số lượng: 20",
        "Image": "https://cf.shopee.vn/file/vn-11134207-7ra0g-m8vmb1dt0xfo70",
        "Original Link": "https://s.shopee.vn/809sHCliHX",
        "Affiliate Link": "https://shorten.asia/WHKXpgxU",
        "Scraping Time": "29-05 Khung: 12:00"
    },
    {
        "Product Name": "Pin Maxell 2A sử dụng cho micro hát karaoke, đồng hồ treo tường, remote, chuột máy tính...",
        "Current Price": "9.000 ₫",
        "Original Price": "35.000 ₫",
        "Percent Badge": "-74%",
        "Amount Info": "Số lượng: 25",
        "Image": "https://cf.shopee.vn/file/vn-11134201-7r98o-lz74hw2r3ichd0",
        "Original Link": "https://s.shopee.vn/AUrDFncCD2",
        "Affiliate Link": "https://shorten.asia/thFdH3fH",
        "Scraping Time": "29-05 Khung: 12:00"
    },
    {
        "Product Name": "Combo 10 Miếng Mặt Nạ Nội Địa Trung Cấp Ẩm Dưỡng Trắng Da Đa Dạng Mẫu Mã",
        "Current Price": "9.000 ₫",
        "Original Price": "35.000 ₫",
        "Percent Badge": "-74%",
        "Amount Info": "Số lượng: 25",
        "Image": "https://cf.shopee.vn/file/vn-11134207-7ras8-mcvn2wq299p8c3",
        "Original Link": "https://s.shopee.vn/AKXn3UcpY1",
        "Affiliate Link": "https://shorten.asia/sgpK1X7S",
        "Scraping Time": "29-05 Khung: 12:00"
    },
    {
        "Product Name": "Sốt Tắc Chua Chua Ngọt Ngọt Cay Nhẹ Nhà Làm - Vị Đậm Đà Thơm Tắc  - Sốt Tắc Chấm Bánh Tráng Phơi Sương - Tipo Food",
        "Current Price": "9.000 ₫",
        "Original Price": "35.000 ₫",
        "Percent Badge": "-74%",
        "Amount Info": "Số lượng: 29",
        "Image": "https://cf.shopee.vn/file/vn-11134207-7ra0g-m746gonms1gn49",
        "Original Link": "https://s.shopee.vn/AAEMrBdSt0",
        "Affiliate Link": "https://shorten.asia/xu9qxNAN",
        "Scraping Time": "29-05 Khung: 12:00"
    },
    {
        "Product Name": "200 chiếc Khẩu trang 6D JULI PRO MASK Cao Cấp Chính Hãng 3 lớp kháng khuẩn chống nắng & tia UV",
        "Current Price": "16.000 ₫",
        "Original Price": "60.000 ₫",
        "Percent Badge": "-73%",
        "Amount Info": "Số lượng: 15,984",
        "Image": "https://cf.shopee.vn/file/vn-11134207-81ztc-mnjxq73gl820b1",
        "Original Link": "https://s.shopee.vn/9zuwese6Dz",
        "Affiliate Link": "https://shorten.asia/VpJUT2u5",
        "Scraping Time": "29-05 Khung: 12:00"
    },
    {
        "Product Name": "Combo 5 cục Cao Su Chùi Keo Dụng Cụ Làm Đồ Da - Da Thuộc Sài Gòn",
        "Current Price": "9.000 ₫",
        "Original Price": "31.000 ₫",
        "Percent Badge": "-71%",
        "Amount Info": "Số lượng: 25",
        "Image": "https://cf.shopee.vn/file/sg-11134201-7rdw5-m1l4kvjyvmm59b",
        "Original Link": "https://s.shopee.vn/9pbWSZejYy",
        "Affiliate Link": "https://shorten.asia/DRGwsKAZ",
        "Scraping Time": "29-05 Khung: 12:00"
    },
    {
        "Product Name": "Phụ Kiện Giày Trang Trí Giày Dễ Thương KT Cat Katie Hình Động Vật Và Trái Cây Dép Nữ Quyến Rũ Trang Trí Giày Quyến Rũ Nút Đeo Chéo Khóa Giày Hợp Thời Trang Miếng Dán Giày",
        "Current Price": "4.000 ₫",
        "Original Price": "13.600 ₫",
        "Percent Badge": "-71%",
        "Amount Info": "Số lượng: 4,900",
        "Image": "https://cf.shopee.vn/file/sg-11134201-821ec-mgypff4aeqkr00",
        "Original Link": "https://s.shopee.vn/9fI6GGfMtx",
        "Affiliate Link": "https://shorten.asia/72cHeaqy",
        "Scraping Time": "29-05 Khung: 12:00"
    },
    {
        "Product Name": "[TẶNG 12 NHÃN VỞ] Vở Ô Ly Tập Học Sinh Hoạt Hình Dễ Thương Deli  4/5 Ô Ly 48/80 Trang - Giấy Dày Tập Viết Luyên Chữ Đẹp",
        "Current Price": "9.000 ₫",
        "Original Price": "30.000 ₫",
        "Percent Badge": "-70%",
        "Amount Info": "Số lượng: 150",
        "Image": "https://cf.shopee.vn/file/sg-11134201-7qvfn-lk4zxg1ijdvpe6",
        "Original Link": "https://s.shopee.vn/9Uyg3xg0Ew",
        "Affiliate Link": "https://shorten.asia/zdsVBXN9",
        "Scraping Time": "29-05 Khung: 12:00"
    },
    {
        "Product Name": "Chén Nấu Sáp Wax Lông Silicon RARE BEAUTY Dụng Cụ Nấu Sáp Chuyên Dụng Cao Cấp Siêu Nhỏ Gọn Tiện Lợi",
        "Current Price": "9.000 ₫",
        "Original Price": "30.000 ₫",
        "Percent Badge": "-70%",
        "Amount Info": "Số lượng: 30",
        "Image": "https://cf.shopee.vn/file/vn-11134207-7ras8-m545t2x7idyu58",
        "Original Link": "https://s.shopee.vn/9KfFregdZv",
        "Affiliate Link": "https://shorten.asia/RyrXmA1k",
        "Scraping Time": "29-05 Khung: 12:00"
    },
    {
        "Product Name": "THEWOLF Vớ Cotton - Màu Đen",
        "Current Price": "9.000 ₫",
        "Original Price": "30.000 ₫",
        "Percent Badge": "-70%",
        "Amount Info": "Số lượng: 20",
        "Image": "https://cf.shopee.vn/file/vn-11134207-7ras8-m2qbnm7d34ee83",
        "Original Link": "https://s.shopee.vn/1BJY8eBj9M",
        "Affiliate Link": "https://shorten.asia/2KAsf4FJ",
        "Scraping Time": "29-05 Khung: 12:00"
    },
    {
        "Product Name": "Dép tông quai ngang nữ nhiều màu đế bệt chất liệu nhựa dẻo mềm rửa nước thoải mái HM092",
        "Current Price": "29.000 ₫",
        "Original Price": "90.000 ₫",
        "Percent Badge": "-68%",
        "Amount Info": "Số lượng: 25",
        "Image": "https://cf.shopee.vn/file/vn-11134207-7ra0g-m73nid9kbpzsb1",
        "Original Link": "https://s.shopee.vn/1107wLCMUL",
        "Affiliate Link": "https://shorten.asia/HZXQcUQu",
        "Scraping Time": "29-05 Khung: 12:00"
    },
    {
        "Product Name": "1 GÓI MÌ CAY NHÀ PACO FOOD KÈM SÚP ĐỘC QUYỀN TIỆN LỢI-ĐƠN GIẢN-NGON",
        "Current Price": "23.000 ₫",
        "Original Price": "70.000 ₫",
        "Percent Badge": "-67%",
        "Amount Info": "Số lượng: 50",
        "Image": "https://cf.shopee.vn/file/vn-11134207-7ras8-mci0868jlui592",
        "Original Link": "https://s.shopee.vn/qghk2CzpK",
        "Affiliate Link": "https://shorten.asia/6kQBgHBM",
        "Scraping Time": "29-05 Khung: 12:00"
    },
    {
        "Product Name": "Pink Fine Long Lanh Trong Suốt Nắp Lật Tổ Chức Dung Tích Lớn Đa Năng Chống Bụi Sundry Photocard Văn Phòng Phẩm Hộp Bảo Quản",
        "Current Price": "21.600 ₫",
        "Original Price": "64.800 ₫",
        "Percent Badge": "-67%",
        "Amount Info": "Số lượng: 300",
        "Image": "https://cf.shopee.vn/file/sg-11134201-7rdvn-m0e8gcelxtps2d",
        "Original Link": "https://s.shopee.vn/gNHXjDdAJ",
        "Affiliate Link": "https://shorten.asia/U3UFDbvS",
        "Scraping Time": "29-05 Khung: 12:00"
    },
    {
        "Product Name": "Bàn Ủi Hơi Nước Cầm Tay Bomidi GS01- 140ml Công Suất Lớn 1200W hiệu suất lớn Có bảo hành lỗi 1 đổi 1",
        "Current Price": "339.000 ₫",
        "Original Price": "950.000 ₫",
        "Percent Badge": "-64%",
        "Amount Info": "Số lượng: 10",
        "Image": "https://cf.shopee.vn/file/vn-11134207-7ras8-mbp67blrzczy8f",
        "Original Link": "https://s.shopee.vn/W3rLQEGVI",
        "Affiliate Link": "https://shorten.asia/BFWFh2nm",
        "Scraping Time": "29-05 Khung: 12:00"
    },
    {
        "Product Name": "Ugreen Ốp Điện Thoại Trong Suốt Từ Tính Chống Va Đập Cho iPhone 15 16 17 Pro Max",
        "Current Price": "112.000 ₫",
        "Original Price": "309.000 ₫",
        "Percent Badge": "-64%",
        "Amount Info": "Số lượng: 510",
        "Image": "https://cf.shopee.vn/file/cn-11134207-7qukw-lgnayi5u0focfe",
        "Original Link": "https://s.shopee.vn/LkR97EtqH",
        "Affiliate Link": "https://shorten.asia/rGnzwh7E",
        "Scraping Time": "29-05 Khung: 12:00"
    },
    {
        "Product Name": "Túi Chống Sốc Bảo Vệ Laptop Có Lót Sốp Đệm Chống Va Đập Chống Trầy Xước Đựng Vừa Các Dòng Máy Tính. 13 - 14 -15.6inch",
        "Current Price": "42.750 ₫",
        "Original Price": "118.000 ₫",
        "Percent Badge": "-64%",
        "Amount Info": "Số lượng: 40",
        "Image": "https://cf.shopee.vn/file/vn-11134207-7r98o-lm24cqjrr0m772",
        "Original Link": "https://s.shopee.vn/BR0woFXBG",
        "Affiliate Link": "https://shorten.asia/DvgsNtSw",
        "Scraping Time": "29-05 Khung: 12:00"
    },
    {
        "Product Name": "Dép Dán Dép Trang Trí Kẹo Đồ Chơi Dán Bánh Mì Chocolate Hoạt Hình Dễ Thương Sáng Tạo Dán Dép Hợp Thời Trang Charm Dán Thích Hợp Cho Giày Có Lỗ 3D Phụ Kiện Ba Chiều",
        "Current Price": "4.000 ₫",
        "Original Price": "11.000 ₫",
        "Percent Badge": "-64%",
        "Amount Info": "Số lượng: 4,350",
        "Image": "https://cf.shopee.vn/file/sg-11134201-821dl-mh1kju74658tfe",
        "Original Link": "https://s.shopee.vn/17akVGAWF",
        "Affiliate Link": "https://shorten.asia/257ekaY9",
        "Scraping Time": "29-05 Khung: 12:00"
    },
    {
        "Product Name": "[BEST SELLER] Vali Kéo MIAvn Larita ROTA - Size 20/24/28, Nhựa PP Dẻo Siêu Bền, Hạn Chế Bể Vỡ, Khoá TSA, Bảo Hành TĐ",
        "Current Price": "799.000 ₫",
        "Original Price": "2.150.000 ₫",
        "Percent Badge": "-63%",
        "Amount Info": "Số lượng: 200",
        "Image": "https://cf.shopee.vn/file/vn-11134207-81ztc-molcpgqivzm4ad",
        "Original Link": "https://s.shopee.vn/2Vovj66eRk",
        "Affiliate Link": "https://shorten.asia/YP7cXKyK",
        "Scraping Time": "29-05 Khung: 12:00"
    },
    {
        "Product Name": "Cờ Lê Hai Đầu Đa Năng Deli Đa Dạng Kích Thước - Chất Liệu Cao Cấp Chống Mòn, Gỉ Sử Dụng Lâu Dài",
        "Current Price": "29.000 ₫",
        "Original Price": "78.000 ₫",
        "Percent Badge": "-63%",
        "Amount Info": "Số lượng: 25",
        "Image": "https://cf.shopee.vn/file/vn-11134207-81ztc-mltcngwfwsn64c",
        "Original Link": "https://s.shopee.vn/2LVVWn7Hmj",
        "Affiliate Link": "https://shorten.asia/rUaZm5d1",
        "Scraping Time": "29-05 Khung: 12:00"
    },
    {
        "Product Name": "Tất đùi trong suốt siêu mỏng có dây treo Kata 12611",
        "Current Price": "29.000 ₫",
        "Original Price": "78.000 ₫",
        "Percent Badge": "-63%",
        "Amount Info": "Số lượng: 20",
        "Image": "https://cf.shopee.vn/file/vn-11134207-820l4-mj41z0pip7gmbe",
        "Original Link": "https://s.shopee.vn/2BC5KU7v7i",
        "Affiliate Link": "https://shorten.asia/42jU7bND",
        "Scraping Time": "29-05 Khung: 12:00"
    },
    {
        "Product Name": "Dễ Thương Mèo Đen Cá Dây Điện Thoại Dây Buộc Phụ Kiện Camera Túi Charm Mặt Dây Chuyền Trang Trí Sáng Tạo Cặp Đôi Người Bạn",
        "Current Price": "25.300 ₫",
        "Original Price": "69.300 ₫",
        "Percent Badge": "-63%",
        "Amount Info": "Số lượng: 300",
        "Image": "https://cf.shopee.vn/file/sg-11134201-7rd46-m6xetnz4g13v16",
        "Original Link": "https://s.shopee.vn/20sf8B8YSh",
        "Affiliate Link": "https://shorten.asia/tHuvvTHN",
        "Scraping Time": "29-05 Khung: 12:00"
    },
    {
        "Product Name": "Gói 10 cầu chì chân nhỏ dành cho ô tô các loại 5A, 10A, 15A, 20A, 25A, 30A",
        "Current Price": "9.000 ₫",
        "Original Price": "23.000 ₫",
        "Percent Badge": "-61%",
        "Amount Info": "Số lượng: 5",
        "Image": "https://cf.shopee.vn/file/182d72156f9ac847ba50c53a0f3f8d68",
        "Original Link": "https://s.shopee.vn/1qZEvs9Bng",
        "Affiliate Link": "https://shorten.asia/15qrt1n3",
        "Scraping Time": "29-05 Khung: 12:00"
    },
    {
        "Product Name": "Ốp điện thoại chống sốc Matte Armor cho Samsung Galaxy A32 A13 A14 A33 A52 A52S A53 A54 A73 5G A51 4G Vỏ bảo vệ chống trượt",
        "Current Price": "62.640 ₫",
        "Original Price": "157.680 ₫",
        "Percent Badge": "-60%",
        "Amount Info": "Số lượng: 320",
        "Image": "https://cf.shopee.vn/file/sg-11134201-23020-1oi92dinoznv1f",
        "Original Link": "https://s.shopee.vn/1gFojZ9p8f",
        "Affiliate Link": "https://shorten.asia/YpYQFMB5",
        "Scraping Time": "29-05 Khung: 12:00"
    },
    {
        "Product Name": "Bộ Đồ Lót Ren Nửa Ngực Siêu Mỏng Chống Chảy Xệ Kiểu Pháp Quyến Rũ Cho Nữ",
        "Current Price": "50.436 ₫",
        "Original Price": "127.440 ₫",
        "Percent Badge": "-60%",
        "Amount Info": "Số lượng: 1,200",
        "Image": "https://cf.shopee.vn/file/cn-11134207-820l4-mglzurso9ki256",
        "Original Link": "https://s.shopee.vn/1VwOXGASTe",
        "Affiliate Link": "https://shorten.asia/FeGpz8K5",
        "Scraping Time": "29-05 Khung: 12:00"
    },
    {
        "Product Name": "500gr Đậu Gà Mỹ (size 9mm) Thiên Thảo Organic",
        "Current Price": "29.000 ₫",
        "Original Price": "70.000 ₫",
        "Percent Badge": "-59%",
        "Amount Info": "Số lượng: 25",
        "Image": "https://cf.shopee.vn/file/sg-11134201-7qveq-ljcgpk1fraq56c",
        "Original Link": "https://s.shopee.vn/1LcyKxB5od",
        "Affiliate Link": "https://shorten.asia/MmR115qp",
        "Scraping Time": "29-05 Khung: 12:00"
    },
    {
        "Product Name": "Đậu lăng đỏ (Red Lentils) Canada 500gr hữu cơ rất tốt cho sức khoẻ Thiên Thảo Organic",
        "Current Price": "29.000 ₫",
        "Original Price": "70.000 ₫",
        "Percent Badge": "-59%",
        "Amount Info": "Số lượng: 25",
        "Image": "https://cf.shopee.vn/file/sg-11134201-7qvej-ljcjkq3ooef418",
        "Original Link": "https://s.shopee.vn/3qKJJY1Zk8",
        "Affiliate Link": "https://shorten.asia/t3HhsKQ1",
        "Scraping Time": "29-05 Khung: 12:00"
    },
    {
        "Product Name": "Sét 5 Quần lót nữ su lạnh không lộ viền,su đúc tàng hình_7A",
        "Current Price": "29.000 ₫",
        "Original Price": "70.000 ₫",
        "Percent Badge": "-59%",
        "Amount Info": "Số lượng: 40",
        "Image": "https://cf.shopee.vn/file/vn-11134207-7r98o-ltadn625rbnob5",
        "Original Link": "https://s.shopee.vn/3g0t7F2D57",
        "Affiliate Link": "https://shorten.asia/XfkKBen9",
        "Scraping Time": "29-05 Khung: 12:00"
    },
    {
        "Product Name": "[6E] [TẶNG 1 QUÀ ] - Combo 6 Bịch Tã/Bỉm Dán/Quần BIMANA EXTRA CARE HÀN QUỐC Thấm Hút Tốt, Đủ Size NB68 - 4XL42",
        "Current Price": "1.050.000 ₫",
        "Original Price": "2.500.000 ₫",
        "Percent Badge": "-58%",
        "Amount Info": "Số lượng: 50",
        "Image": "https://cf.shopee.vn/file/vn-11134207-81ztc-modvaxfypybl2d",
        "Original Link": "https://s.shopee.vn/3VhSuw2qQ6",
        "Affiliate Link": "https://shorten.asia/WDYwwAsb",
        "Scraping Time": "29-05 Khung: 12:00"
    },
    {
        "Product Name": "Gối cao su non người lớn CECILA Gối Nệm Y Tế có gel lạnh, thiết kế công thái học, hỗ trợ ngủ nhanh, giảm đau cổ vai gáy",
        "Current Price": "189.000 ₫",
        "Original Price": "450.000 ₫",
        "Percent Badge": "-58%",
        "Amount Info": "Số lượng: 140",
        "Image": "https://cf.shopee.vn/file/vn-11134207-81ztc-mn3rldkt9o8x55",
        "Original Link": "https://s.shopee.vn/3LO2id3Tl5",
        "Affiliate Link": "https://shorten.asia/hy4RU5Ae",
        "Scraping Time": "29-05 Khung: 12:00"
    },
    {
        "Product Name": "LANBENASữa Rửa Mặt  Vitamin C - Giúp Làm Sạch Sâu, Làm Sáng Kiểm Soát Dầu Nhờn, Dưỡng ẩm, Làm Dịu, Làm Sạch Da Chết Skincare",
        "Current Price": "100.300 ₫",
        "Original Price": "240.000 ₫",
        "Percent Badge": "-58%",
        "Amount Info": "Số lượng: 600",
        "Image": "https://cf.shopee.vn/file/cn-11134207-7ras8-mbm53hqehwae4f",
        "Original Link": "https://s.shopee.vn/3B4cWK4764",
        "Affiliate Link": "https://shorten.asia/yGZ4bR6G",
        "Scraping Time": "29-05 Khung: 12:00"
    },
    {
        "Product Name": "Bộ Vệ Sinh Laptop Đầy Đủ Dụng Cụ Chuyên Dụng Làm Sạch Màn Hình Và Bàn Phím Hiệu Quả, Vệ Sinh Laptop",
        "Current Price": "29.000 ₫",
        "Original Price": "69.000 ₫",
        "Percent Badge": "-58%",
        "Amount Info": "Số lượng: 24",
        "Image": "https://cf.shopee.vn/file/vn-11134207-7ras8-mcyfxk73l96506",
        "Original Link": "https://s.shopee.vn/30lCK14kR3",
        "Affiliate Link": "https://shorten.asia/HV38hAGU",
        "Scraping Time": "29-05 Khung: 12:00"
    },
    {
        "Product Name": "Sữa Rửa Mặt 3W Clinic 100ml - Dưỡng Da Tinh Khiết, Chiết Xuất Thiên Nhiên, Làm Sạch & Cân Bằng Da",
        "Current Price": "29.000 ₫",
        "Original Price": "69.000 ₫",
        "Percent Badge": "-58%",
        "Amount Info": "Số lượng: 25",
        "Image": "https://cf.shopee.vn/file/vn-11134207-81ztc-mlxsmfls3if556",
        "Original Link": "https://s.shopee.vn/2qRm7i5Nm2",
        "Affiliate Link": "https://shorten.asia/DPcYM5Zx",
        "Scraping Time": "29-05 Khung: 12:00"
    },
    {
        "Product Name": "Áo Polo Nam POLOMAN Vải CVC Cá Sấu Cotton Cao Cấp, Thiết Kế Trẻ Trung, Thanh Lịch, Đẳng Cấp",
        "Current Price": "195.000 ₫",
        "Original Price": "458.000 ₫",
        "Percent Badge": "-57%",
        "Amount Info": "Số lượng: 8,400",
        "Image": "https://cf.shopee.vn/file/sg-11134201-7rdy0-mdswig28ij1072",
        "Original Link": "https://s.shopee.vn/2g8LvP6171",
        "Affiliate Link": "https://shorten.asia/AwRRkCCX",
        "Scraping Time": "29-05 Khung: 12:00"
    },
    {
        "Product Name": "Áo khoác Cardigan dáng dài thun co giãn basic thanh lịch mặc thu đông kiểu dáng hotgirl",
        "Current Price": "42.400 ₫",
        "Original Price": "99.000 ₫",
        "Percent Badge": "-57%",
        "Amount Info": "Số lượng: 240",
        "Image": "https://cf.shopee.vn/file/vn-11134207-820l4-memd5litezgn59",
        "Original Link": "https://s.shopee.vn/5ApgtzwV2W",
        "Affiliate Link": "https://shorten.asia/wpKt35eM",
        "Scraping Time": "29-05 Khung: 12:00"
    },
    {
        "Product Name": "[Đọc Kỹ Mô Tả Ạ] Slime Mini Basic 2oz 60ml Dẻo Không Dính Tay/ Slime Cơ Bản Màu Sắc Tự Chọn/ Đồ Chơi Chất Nhờn Ma Quái",
        "Current Price": "9.000 ₫",
        "Original Price": "21.000 ₫",
        "Percent Badge": "-57%",
        "Amount Info": "Số lượng: 5",
        "Image": "https://cf.shopee.vn/file/vn-11134207-7r98o-ltnrl9f8etjebe",
        "Original Link": "https://s.shopee.vn/50WGhgx8NV",
        "Affiliate Link": "https://shorten.asia/pP41BJqW",
        "Scraping Time": "29-05 Khung: 12:00"
    },
    {
        "Product Name": "Dép Dán Dép Dép Trang Trí Phụ Kiện Giày Ngọc Trai Hoa Trắng Tím Bướm Kim Cương Bộ Trang Sức Nhiều Kiểu Trang Trí Dép Charm Dán Thích Hợp Cho Giày Có Lỗ Phụ Kiện Ba Chiều (A)",
        "Current Price": "16.000 ₫",
        "Original Price": "36.000 ₫",
        "Percent Badge": "-56%",
        "Amount Info": "Số lượng: 1,650",
        "Image": "https://cf.shopee.vn/file/sg-11134201-821d7-mh05l9s4vz7w90",
        "Original Link": "https://s.shopee.vn/4qCqVNxliU",
        "Affiliate Link": "https://shorten.asia/6wm4FHQH",
        "Scraping Time": "29-05 Khung: 12:00"
    },
    {
        "Product Name": "Dép Dán Dép Dép Trang Trí Trắng Tím Bướm Kim Cương Bộ Trang Sức Kim Cương Chăm Sóc Gấu Nhiều Kiểu Dép Tùy Chọn Nhãn Dán Quyến Rũ Thích Hợp Cho Giày Lỗ Phụ Kiện Ba Chiều",
        "Current Price": "16.000 ₫",
        "Original Price": "36.000 ₫",
        "Percent Badge": "-56%",
        "Amount Info": "Số lượng: 1,650",
        "Image": "https://cf.shopee.vn/file/sg-11134201-821df-mh1g1lbb7or0a1",
        "Original Link": "https://s.shopee.vn/4ftQJ4yP3T",
        "Affiliate Link": "https://shorten.asia/fj2kwUAk",
        "Scraping Time": "29-05 Khung: 12:00"
    },
    {
        "Product Name": "Dép Dán Phụ Kiện Giày Bộ 12 Món Phô Mai Bộ Nhạc Giai Điệu Bộ Đa Phong Cách Nút Có Thể Tháo Rời Thích Hợp Cho Giày Có Lỗ Phụ Kiện Ba Chiều 3D",
        "Current Price": "11.000 ₫",
        "Original Price": "25.000 ₫",
        "Percent Badge": "-56%",
        "Amount Info": "Số lượng: 2,250",
        "Image": "https://cf.shopee.vn/file/sg-11134201-821dm-mh38f2t40365ac",
        "Original Link": "https://s.shopee.vn/4Va06lz2OS",
        "Affiliate Link": "https://shorten.asia/vNs6rsgD",
        "Scraping Time": "29-05 Khung: 12:00"
    },
    {
        "Product Name": "Dép Dán Phụ Kiện Giày 13 Miếng Xingdailu Mùa Hè Sóng Bộ Đa Phong Cách Nút Có Thể Tháo Rời Thích Hợp Cho Giày Có Lỗ Phụ Kiện Ba Chiều 3D",
        "Current Price": "11.000 ₫",
        "Original Price": "25.000 ₫",
        "Percent Badge": "-56%",
        "Amount Info": "Số lượng: 2,250",
        "Image": "https://cf.shopee.vn/file/sg-11134201-821eu-mh38ibvysxs885",
        "Original Link": "https://s.shopee.vn/4LGZuSzfjR",
        "Affiliate Link": "https://shorten.asia/G2SRUbhe",
        "Scraping Time": "29-05 Khung: 12:00"
    },
    {
        "Product Name": "Dép Dán Dép Sandal Trang Trí Mèo Dễ Thương kt7-Bộ Đồ Chơi Thực Phẩm Burger Bộ Đa Phong Cách Nút Có Thể Tháo Rời Thích Hợp Cho Giày Có Lỗ Phụ Kiện Ba Chiều 3D",
        "Current Price": "11.000 ₫",
        "Original Price": "25.000 ₫",
        "Percent Badge": "-56%",
        "Amount Info": "Số lượng: 2,250",
        "Image": "https://cf.shopee.vn/file/sg-11134201-821ds-mh0446gbrdhp47",
        "Original Link": "https://s.shopee.vn/4Ax9iA0J4Q",
        "Affiliate Link": "https://shorten.asia/ysm3egKP",
        "Scraping Time": "29-05 Khung: 12:00"
    },
    {
        "Product Name": "Pin sạc dự phòng Ugreen Nexode 25000mAh-200w/20000mAh-130w/12000mAh-100w | Màn LED | Bảo hành 18 tháng",
        "Current Price": "1.350.000 ₫",
        "Original Price": "2.990.000 ₫",
        "Percent Badge": "-55%",
        "Amount Info": "Số lượng: 20",
        "Image": "https://cf.shopee.vn/file/sg-11134201-7rd46-m7w9m3597o9jd5",
        "Original Link": "https://s.shopee.vn/40djVr0wPP",
        "Affiliate Link": "https://shorten.asia/uJBUaXfM",
        "Scraping Time": "29-05 Khung: 12:00"
    },
    {
        "Product Name": "Quần Jean Ống Đứng LODES CLUB Form Hàn Quốc Chất Denim Cotton Mềm Mại Dành Cho Nam, Menswear Wash",
        "Current Price": "174.000 ₫",
        "Original Price": "390.000 ₫",
        "Percent Badge": "-55%",
        "Amount Info": "Số lượng: 330",
        "Image": "https://cf.shopee.vn/file/vn-11134207-81ztc-mn1pxznaesxt2b",
        "Original Link": "https://s.shopee.vn/6L1eI8s3fs",
        "Affiliate Link": "https://shorten.asia/F5uTDgf5",
        "Scraping Time": "29-05 Khung: 12:00"
    },
    {
        "Product Name": "Sỉ Combo 100 chiếc khẩu trang 6A Mask 4 lớp Mẫu Mới Quai Mềm, Nhiều Màu Hottrend",
        "Current Price": "9.000 ₫",
        "Original Price": "20.000 ₫",
        "Percent Badge": "-55%",
        "Amount Info": "Số lượng: 30",
        "Image": "https://cf.shopee.vn/file/vn-11134207-7ras8-m4vkn9nwcgqg6f",
        "Original Link": "https://s.shopee.vn/6VL4URrQKv",
        "Affiliate Link": "https://shorten.asia/Xtv9cqxe",
        "Scraping Time": "29-05 Khung: 12:00"
    },
    {
        "Product Name": "[ NHỎ - GỌN - NHẸ ] Vali Kéo LUG Holdall MP809 - Size 20, Size 24, Size 28: Nhựa PP chống bể vỡ, Khoá Số Bảo Mật An Toàn",
        "Current Price": "909.000 ₫",
        "Original Price": "1.980.000 ₫",
        "Percent Badge": "-54%",
        "Amount Info": "Số lượng: 90",
        "Image": "https://cf.shopee.vn/file/vn-11134207-81ztc-moot7s6g7wg226",
        "Original Link": "https://s.shopee.vn/60OntWtKLq",
        "Affiliate Link": "https://shorten.asia/DKcymNuM",
        "Scraping Time": "29-05 Khung: 12:00"
    },
    {
        "Product Name": "Combo sạc nhanh 30W UGREEN cho iPhone 8 đến iPhone 14 series - Củ 20W 1C & Cáp CtoL đạt chứng chỉ MFi US304",
        "Current Price": "249.000 ₫",
        "Original Price": "539.000 ₫",
        "Percent Badge": "-54%",
        "Amount Info": "Số lượng: 20",
        "Image": "https://cf.shopee.vn/file/sg-11134201-7rd53-m769zs1ugwbfa6",
        "Original Link": "https://s.shopee.vn/6AiE5psh0t",
        "Affiliate Link": "https://shorten.asia/cGkRc7M8",
        "Scraping Time": "29-05 Khung: 12:00"
    },
    {
        "Product Name": "Xịt khử mùi toàn thân, lăn khử mùi BEUFRESH ngăn tiết mồ hôi, hạn chế mùi cơ thể 30ml",
        "Current Price": "162.000 ₫",
        "Original Price": "349.000 ₫",
        "Percent Badge": "-54%",
        "Amount Info": "Số lượng: 200",
        "Image": "https://cf.shopee.vn/file/vn-11134207-81ztc-moqd36f0h9u47d",
        "Original Link": "https://s.shopee.vn/5flxUuub1o",
        "Affiliate Link": "https://shorten.asia/qBeQnU3x",
        "Scraping Time": "29-05 Khung: 12:00"
    },
    {
        "Product Name": "COMBO 2 Bịch mỗi bịch 100gr Nấm Đông Cô sai 30 sấy khô ăn chay ăn kiêng giảm cân loại 1 Thiên Thảo Organic",
        "Current Price": "54.000 ₫",
        "Original Price": "118.000 ₫",
        "Percent Badge": "-54%",
        "Amount Info": "Số lượng: 50",
        "Image": "https://cf.shopee.vn/file/sg-11134201-7qvd3-ljcgeoi8px0z83",
        "Original Link": "https://s.shopee.vn/5q5NhDtxgr",
        "Affiliate Link": "https://shorten.asia/Fpn6wUG3",
        "Scraping Time": "29-05 Khung: 12:00"
    },
    {
        "Product Name": "【Bán chạy】JMCY Chì kẻ mày đầu siêu mảnh chống nước và chống lem màu sắc lâu trôi dễ dàng tạo nên hàng lông mày tự nhiên ba chiều và hoàn hảo",
        "Current Price": "50.000 ₫",
        "Original Price": "109.000 ₫",
        "Percent Badge": "-54%",
        "Amount Info": "Số lượng: 1,000",
        "Image": "https://cf.shopee.vn/file/cn-11134207-820l4-morqadn1tzwr2f",
        "Original Link": "https://s.shopee.vn/5L976Ivrhm",
        "Affiliate Link": "https://shorten.asia/4WfnvXvm",
        "Scraping Time": "29-05 Khung: 12:00"
    },
    {
        "Product Name": "Móc đá lốp xe móc đá lốp xe dụng cụ cạo đá làm sạch bằng thép không gỉ móc đá khe hở công cụ loại bỏ đá",
        "Current Price": "22.000 ₫",
        "Original Price": "47.547 ₫",
        "Percent Badge": "-54%",
        "Amount Info": "Số lượng: 7",
        "Image": "https://cf.shopee.vn/file/sg-11134201-824hp-mee1dynvu1vnd6",
        "Original Link": "https://s.shopee.vn/5VSXIbvEMp",
        "Affiliate Link": "https://shorten.asia/3mZh5KaA",
        "Scraping Time": "29-05 Khung: 12:00"
    },
    {
        "Product Name": "Aimilo Cuộn 500 miếng dán hoạt hình ngộ nghĩnh tem dán sticker thank you gói hàng phụ kiện quà tặng",
        "Current Price": "11.900 ₫",
        "Original Price": "25.800 ₫",
        "Percent Badge": "-54%",
        "Amount Info": "Số lượng: 50",
        "Image": "https://cf.shopee.vn/file/vn-11134207-7ras8-m0r2imc93x5b03",
        "Original Link": "https://s.shopee.vn/7fX1samyyG",
        "Affiliate Link": "https://shorten.asia/bAPbNzhd",
        "Scraping Time": "29-05 Khung: 12:00"
    },
    {
        "Product Name": "[2pcs]Combo tiện lợi Máy tăm nước sóng siêu âm usmile C10+Y10S Chăm răng thông minh",
        "Current Price": "1.691.000 ₫",
        "Original Price": "3.590.000 ₫",
        "Percent Badge": "-53%",
        "Amount Info": "Số lượng: 20",
        "Image": "https://cf.shopee.vn/file/vn-11134207-81ztc-moqjy5mc4zd869",
        "Original Link": "https://s.shopee.vn/7pqS4tmLdJ",
        "Affiliate Link": "https://shorten.asia/n1C81E21",
        "Scraping Time": "29-05 Khung: 12:00"
    },
    {
        "Product Name": "Quạt tay JisuLife Pro1/S siêu nhỏ gọn gió siêu mạnh pin trâu 100 cấp độ điều chỉnh màn hình LED sạc điện để bàn dã ngoại",
        "Current Price": "769.000 ₫",
        "Original Price": "1.638.000 ₫",
        "Percent Badge": "-53%",
        "Amount Info": "Số lượng: 300",
        "Image": "https://cf.shopee.vn/file/vn-11134207-81ztc-mk28knlhlnnr72",
        "Original Link": "https://s.shopee.vn/7KuBTyoFeE",
        "Affiliate Link": "https://shorten.asia/Q9SvEPQH",
        "Scraping Time": "29-05 Khung: 12:00"
    },
    {
        "Product Name": "Bộ Quần Áo Nam  WINFIT MotionLine Chất Vải ComfortLite, Thấm Hút Mồ Hôi, Form Regular Thoải Mái",
        "Current Price": "189.000 ₫",
        "Original Price": "400.000 ₫",
        "Percent Badge": "-53%",
        "Amount Info": "Số lượng: 95",
        "Image": "https://cf.shopee.vn/file/vn-11134207-81ztc-mmqbkrdf4zk20f",
        "Original Link": "https://s.shopee.vn/9fI6GGiShA",
        "Affiliate Link": "https://shorten.asia/uBwW944F",
        "Scraping Time": "29-05 Khung: 12:00"
    },
    {
        "Product Name": "Kem Tạo Khối Dạng Lỏng SHEGLAM Hiệu Ứng Lì, Lên Màu Chuẩn, Tự Nhiên, Lâu Trôi, Trang Điểm Mặt",
        "Current Price": "126.907 ₫",
        "Original Price": "267.300 ₫",
        "Percent Badge": "-53%",
        "Amount Info": "Số lượng: 750",
        "Image": "https://cf.shopee.vn/file/cn-11134207-820l4-mfxsh0cjigp61b",
        "Original Link": "https://s.shopee.vn/9pbWSZhpMD",
        "Affiliate Link": "https://shorten.asia/qvjyju2F",
        "Scraping Time": "29-05 Khung: 12:00"
    },
    {
        "Product Name": "Xịt Diệt Mạt Bụi 1500ml, Bình Xịt Diệt Rệp giường, Bình Xịt Diệt Bọ Ve, Bọ Rệp, Hiệu Quả Diệt 100%, Giảm Ngứa Dị Ứng",
        "Current Price": "89.775 ₫",
        "Original Price": "189.000 ₫",
        "Percent Badge": "-53%",
        "Amount Info": "Số lượng: 50",
        "Image": "https://cf.shopee.vn/file/vn-11134207-81ztc-mkhxgerxqsjre1",
        "Original Link": "https://s.shopee.vn/9KfFrejjN8",
        "Affiliate Link": "https://shorten.asia/uXAFXHKf",
        "Scraping Time": "29-05 Khung: 12:00"
    },
    {
        "Product Name": "Bóng Pickleball Chanlong 48 Lỗ Chính Hãng | Box 3 Quả Chuẩn Thi Đấu | Độ Nảy Ổn Định Bền Bỉ",
        "Current Price": "85.000 ₫",
        "Original Price": "179.000 ₫",
        "Percent Badge": "-53%",
        "Amount Info": "Số lượng: 30",
        "Image": "https://cf.shopee.vn/file/vn-11134207-81ztc-mogngzichxj570",
        "Original Link": "https://s.shopee.vn/9Uyg3xj62B",
        "Affiliate Link": "https://shorten.asia/M5VZCgcB",
        "Scraping Time": "29-05 Khung: 12:00"
    },
    {
        "Product Name": "Niche Độc Đáo Thu Đông Khăn Lụa Retro Da Báo In Thắt Lưng Nữ",
        "Current Price": "33.500 ₫",
        "Original Price": "71.000 ₫",
        "Percent Badge": "-53%",
        "Amount Info": "Số lượng: 50",
        "Image": "https://cf.shopee.vn/file/sg-11134201-8259o-mg7lrj9plvkbc5",
        "Original Link": "https://s.shopee.vn/902PT2l036",
        "Affiliate Link": "https://shorten.asia/kW59hfxX",
        "Scraping Time": "29-05 Khung: 12:00"
    },
    {
        "Product Name": "Bàn Chải Lông Mềm Đánh Giày, Chà Sàn, Vệ Sinh Nhà Tắm, Giặt Đồ - Nhựa PPM - 100gram - 17*3 - Đa Chức Năng",
        "Current Price": "9.000 ₫",
        "Original Price": "19.000 ₫",
        "Percent Badge": "-53%",
        "Amount Info": "Số lượng: 35",
        "Image": "https://cf.shopee.vn/file/sg-11134201-7rfie-m96u8mvntzfm46",
        "Original Link": "https://s.shopee.vn/9ALpfLkMi9",
        "Affiliate Link": "https://shorten.asia/jH5zzrDr",
        "Scraping Time": "29-05 Khung: 12:00"
    },
    {
        "Product Name": "Quần jeans ống cong ZGO dáng rộng thụng wash chất vải dày dặn nam nữ đều mặc được Qzg17",
        "Current Price": "239.000 ₫",
        "Original Price": "498.000 ₫",
        "Percent Badge": "-52%",
        "Amount Info": "Số lượng: 141",
        "Image": "https://cf.shopee.vn/file/vn-11134207-81ztc-moeu0gtpowllc0",
        "Original Link": "https://s.shopee.vn/8fPZ4QmGj4",
        "Affiliate Link": "https://shorten.asia/Tqdt1sYF",
        "Scraping Time": "29-05 Khung: 12:00"
    },
    {
        "Product Name": "Áo sơ mi kiểu kẻ sọc tay dài cổ tàu form lửng | Vana Shirt - B.Y Tea",
        "Current Price": "221.600 ₫",
        "Original Price": "460.000 ₫",
        "Percent Badge": "-52%",
        "Amount Info": "Số lượng: 26",
        "Image": "https://cf.shopee.vn/file/vn-11134207-81ztc-mmgca1xfqhvn1e",
        "Original Link": "https://s.shopee.vn/8pizGjldO7",
        "Affiliate Link": "https://shorten.asia/6r54Ur3p",
        "Scraping Time": "29-05 Khung: 12:00"
    },
    {
        "Product Name": "AB HOUSE - Áo thun Boxy form rộng SUMMER thời trang nam nữ",
        "Current Price": "218.000 ₫",
        "Original Price": "450.000 ₫",
        "Percent Badge": "-52%",
        "Amount Info": "Số lượng: 450",
        "Image": "https://cf.shopee.vn/file/vn-11134207-81ztc-mmluvv5dtg5f9d",
        "Original Link": "https://s.shopee.vn/8KmifonXP2",
        "Affiliate Link": "https://shorten.asia/hEyTJ19g",
        "Scraping Time": "29-05 Khung: 12:00"
    },
    {
        "Product Name": "(Nội Địa Nhật) Chip Chắn Sóng Điện Từ Hitoki - Cô Gái Sakura",
        "Current Price": "98.000 ₫",
        "Original Price": "205.000 ₫",
        "Percent Badge": "-52%",
        "Amount Info": "Số lượng: 30",
        "Image": "https://cf.shopee.vn/file/vn-11134207-7r98o-lzym7geh6gm9b9",
        "Original Link": "https://s.shopee.vn/8V68s7mu45",
        "Affiliate Link": "https://shorten.asia/z4hA9s67",
        "Scraping Time": "29-05 Khung: 12:00"
    },
    {
        "Product Name": "Kệ đựng đồ rửa chén inox 304 2 tầng có khay kèm đĩa dốc 45 độ thoát nước tiện lợi",
        "Current Price": "56.100 ₫",
        "Original Price": "118.000 ₫",
        "Percent Badge": "-52%",
        "Amount Info": "Số lượng: 30",
        "Image": "https://cf.shopee.vn/file/vn-11134207-7ras8-m2g4drhxzph07b",
        "Original Link": "https://s.shopee.vn/809sHCoo50",
        "Affiliate Link": "https://shorten.asia/1ufdsNex",
        "Scraping Time": "29-05 Khung: 12:00"
    },
    {
        "Product Name": "Retro Nữ Nơ Kẹp Thu Đông Lớn Thanh Lịch Cá Mập Kẹp",
        "Current Price": "55.080 ₫",
        "Original Price": "114.480 ₫",
        "Percent Badge": "-52%",
        "Amount Info": "Số lượng: 71",
        "Image": "https://cf.shopee.vn/file/sg-11134201-821fw-mgousd7qir626b",
        "Original Link": "https://s.shopee.vn/8ATITVoAk3",
        "Affiliate Link": "https://shorten.asia/RnAjpwTU",
        "Scraping Time": "29-05 Khung: 12:00"
    },
    {
        "Product Name": "Thu Đông Nhung Tam Giác Nữ Kẹp Kích Thước Lớn Thời Trang Sang Trọng Kẹp Tóc",
        "Current Price": "45.000 ₫",
        "Original Price": "94.000 ₫",
        "Percent Badge": "-52%",
        "Amount Info": "Số lượng: 38",
        "Image": "https://cf.shopee.vn/file/sg-11134201-821e2-mghlezccz85lda",
        "Original Link": "https://s.shopee.vn/7fX1saq4ky",
        "Affiliate Link": "https://shorten.asia/RsbxaD7B",
        "Scraping Time": "29-05 Khung: 12:00"
    },
    {
        "Product Name": "Vỉ đạn bạc bấm lỗ tai, khuyên bấm lỗ tai và núm bịt mua thêm cho máy bấm lỗ tai",
        "Current Price": "29.000 ₫",
        "Original Price": "60.000 ₫",
        "Percent Badge": "-52%",
        "Amount Info": "Số lượng: 10",
        "Image": "https://cf.shopee.vn/file/vn-11134207-7ras8-m4pwxxiojrbb16",
        "Original Link": "https://s.shopee.vn/7pqS4tpRQ1",
        "Affiliate Link": "https://shorten.asia/mFAASzSN",
        "Scraping Time": "29-05 Khung: 12:00"
    },
    {
        "Product Name": "Tất Đá Bóng, Vớ Đá Banh Chống Trơn Chống Trượt Sân Cỏ Co Giãn",
        "Current Price": "29.000 ₫",
        "Original Price": "60.000 ₫",
        "Percent Badge": "-52%",
        "Amount Info": "Số lượng: 25",
        "Image": "https://cf.shopee.vn/file/vn-11134207-7r98o-llzu9rk8il0f11",
        "Original Link": "https://s.shopee.vn/7KuBTyrLQw",
        "Affiliate Link": "https://shorten.asia/WYg2EFfp",
        "Scraping Time": "29-05 Khung: 12:00"
    },
    {
        "Product Name": "Tháp vịt 9 tầng, tháp xếp vòng cầu vồng nhiều màu sắc cho bé",
        "Current Price": "29.000 ₫",
        "Original Price": "60.000 ₫",
        "Percent Badge": "-52%",
        "Amount Info": "Số lượng: 25",
        "Image": "https://cf.shopee.vn/file/vn-11134207-7r98o-lni8vhmtgo31df",
        "Original Link": "https://s.shopee.vn/7VDbgHqi5z",
        "Affiliate Link": "https://shorten.asia/83MzfY8b",
        "Scraping Time": "29-05 Khung: 12:00"
    },
    {
        "Product Name": "[1kg] Phân bón tổng hợp NPK,phân bón Nitrophoska giúp cây tăng trưởng và phát triển toàn diện (PB-0)",
        "Current Price": "29.000 ₫",
        "Original Price": "60.000 ₫",
        "Percent Badge": "-52%",
        "Amount Info": "Số lượng: 50",
        "Image": "https://cf.shopee.vn/file/vn-11134211-7ras8-m15edgv2szujd0",
        "Original Link": "https://s.shopee.vn/70HL5Msc6u",
        "Affiliate Link": "https://shorten.asia/ffWpx7NC",
        "Scraping Time": "29-05 Khung: 12:00"
    },
    {
        "Product Name": "Túi xách nữ đeo chéo túi nữ cầm tay đeo vai thời trang đi học đi làm da nhung loang HAKIDO _TDC292",
        "Current Price": "29.000 ₫",
        "Original Price": "61.000 ₫",
        "Percent Badge": "-52%",
        "Amount Info": "Số lượng: 25",
        "Image": "https://cf.shopee.vn/file/vn-11134207-7ra0g-m8ejunjz9oj245",
        "Original Link": "https://s.shopee.vn/7AalHfrylx",
        "Affiliate Link": "https://shorten.asia/sevFhuYg",
        "Scraping Time": "29-05 Khung: 12:00"
    },
    {
        "Product Name": "Bình Đựng Nước Hoa Quả Detox LocknLock Milky 500ml HAP654, Hàng chính hãng, không chứa BPA - T2CMall",
        "Current Price": "29.000 ₫",
        "Original Price": "60.000 ₫",
        "Percent Badge": "-52%",
        "Amount Info": "Số lượng: 25",
        "Image": "https://cf.shopee.vn/file/vn-11134207-7ras8-mdmvq4ab8c6p3d",
        "Original Link": "https://s.shopee.vn/6feUgktsms",
        "Affiliate Link": "https://shorten.asia/c2PPQkXS",
        "Scraping Time": "29-05 Khung: 12:00"
    },
    {
        "Product Name": "Mũ Cào Cào LS2 MX436 Pioneer Evo ECE2205 1 Kính [Bảo Hành Chính Hãng 2 năm]",
        "Current Price": "3.695.000 ₫",
        "Original Price": "7.540.000 ₫",
        "Percent Badge": "-51%",
        "Amount Info": "Số lượng: 12",
        "Image": "https://cf.shopee.vn/file/vn-11134207-81ztc-mnttgdxx0etd4d",
        "Original Link": "https://s.shopee.vn/6pxut3tFRv",
        "Affiliate Link": "https://shorten.asia/tejp1sbS",
        "Scraping Time": "29-05 Khung: 12:00"
    },
    {
        "Product Name": "[EMEET] Webcam C950 4K dành cho Zoom / Teams / Google Meet",
        "Current Price": "688.000 ₫",
        "Original Price": "1.400.000 ₫",
        "Percent Badge": "-51%",
        "Amount Info": "Số lượng: 50",
        "Image": "https://cf.shopee.vn/file/cn-11134207-820l4-mj9seu2wsg03b8",
        "Original Link": "https://s.shopee.vn/6L1eI8v9Sq",
        "Affiliate Link": "https://shorten.asia/6t6cVmWK",
        "Scraping Time": "29-05 Khung: 12:00"
    },
    {
        "Product Name": "- Quần jeans nữ ống rộng phối line nhúm phần hông tôn dáng che khuyết điểm MINI03",
        "Current Price": "170.999 ₫",
        "Original Price": "349.000 ₫",
        "Percent Badge": "-51%",
        "Amount Info": "Số lượng: 116",
        "Image": "https://cf.shopee.vn/file/vn-11134207-7ra0g-m734thcz70bce7",
        "Original Link": "https://s.shopee.vn/6VL4URuW7t",
        "Affiliate Link": "https://shorten.asia/qKwFEaq8",
        "Scraping Time": "29-05 Khung: 12:00"
    },
    {
        "Product Name": "Nước tẩy keo, Dung dịch tẩy băng keo, Tẩy sạch các vết keo cứng đầu, Băng dính, sticker, Giấy dán tường, Vết son",
        "Current Price": "155.820 ₫",
        "Original Price": "318.000 ₫",
        "Percent Badge": "-51%",
        "Amount Info": "Số lượng: 50",
        "Image": "https://cf.shopee.vn/file/vn-11134207-81ztc-mma27or81zwl2f",
        "Original Link": "https://s.shopee.vn/60OntWwQ8o",
        "Affiliate Link": "https://shorten.asia/5s9dyxUb",
        "Scraping Time": "29-05 Khung: 12:00"
    },
    {
        "Product Name": "LANBENA Pimple Cure Serum (30ml) - Giúp Thu Nhỏ Lỗ Chân Lông Dưỡng Ẩm Chăm Sóc Da  Skincare",
        "Current Price": "146.300 ₫",
        "Original Price": "299.000 ₫",
        "Percent Badge": "-51%",
        "Amount Info": "Số lượng: 900",
        "Image": "https://cf.shopee.vn/file/cn-11134207-820l4-mnbe632wxkw84c",
        "Original Link": "https://s.shopee.vn/6AiE5pvmnr",
        "Affiliate Link": "https://shorten.asia/Wvz9t9N5",
        "Scraping Time": "29-05 Khung: 12:00"
    },
    {
        "Product Name": "Quần mặc nhà unisex vải oxford cao cấp họa tiết kẻ sọc form ống rộng thoải mái QZG05",
        "Current Price": "77.000 ₫",
        "Original Price": "158.000 ₫",
        "Percent Badge": "-51%",
        "Amount Info": "Số lượng: 332",
        "Image": "https://cf.shopee.vn/file/vn-11134207-81ztc-modp4xagg5jiba",
        "Original Link": "https://s.shopee.vn/5flxUuxgom",
        "Affiliate Link": "https://shorten.asia/yTcGjdsV",
        "Scraping Time": "29-05 Khung: 12:00"
    },
    {
        "Product Name": "Hồng Trà, Trà Đen Nguyên Liệu Làm Trà Sữa Trân Châu THƯỢNG HẠNG 500g",
        "Current Price": "68.000 ₫",
        "Original Price": "138.000 ₫",
        "Percent Badge": "-51%",
        "Amount Info": "Số lượng: 50",
        "Image": "https://cf.shopee.vn/file/vn-11134207-7r98o-lyqkhqre5nz5fe",
        "Original Link": "https://s.shopee.vn/5q5NhDx3Tp",
        "Affiliate Link": "https://shorten.asia/ty4hcsgq",
        "Scraping Time": "29-05 Khung: 12:00"
    },
    {
        "Product Name": "Trà Đen, Hồng Trà Nguyên Liệu Làm Trà Sữa Trân Châu Đường Đen Tự Pha THƯỢNG HẠNG 500g",
        "Current Price": "68.000 ₫",
        "Original Price": "138.000 ₫",
        "Percent Badge": "-51%",
        "Amount Info": "Số lượng: 50",
        "Image": "https://cf.shopee.vn/file/vn-11134207-7r98o-lyqmeslqfe01d8",
        "Original Link": "https://s.shopee.vn/5L976IyxUk",
        "Affiliate Link": "https://shorten.asia/2BSxpQXx",
        "Scraping Time": "29-05 Khung: 12:00"
    },
    {
        "Product Name": "Mắt Màu Xám Ống Kính Tiếp Xúc Cho Mắt Ống Kính Màu Mỹ Phẩm Mềm Mắt Kính Làm Đẹp Học Sinh Phong Cách Phương Tây Trang Điểm",
        "Current Price": "51.900 ₫",
        "Original Price": "105.800 ₫",
        "Percent Badge": "-51%",
        "Amount Info": "Số lượng: 1,800",
        "Image": "https://cf.shopee.vn/file/sg-11134201-7rdvc-m012w5jilclg8a",
        "Original Link": "https://s.shopee.vn/5VSXIbyK9n",
        "Affiliate Link": "https://shorten.asia/FsWXNVNt",
        "Scraping Time": "29-05 Khung: 12:00"
    },
    {
        "Product Name": "Áo Thun Nữ Form Rộng Tay Dài  Áo Phông Kẻ Ráp Lăng Phối Cổ Chữ Xinh Xắn Long Sleeve Boxy Hottrend",
        "Current Price": "34.000 ₫",
        "Original Price": "69.000 ₫",
        "Percent Badge": "-51%",
        "Amount Info": "Số lượng: 340",
        "Image": "https://cf.shopee.vn/file/sg-11134201-822x8-mi1w99736rk0e8",
        "Original Link": "https://s.shopee.vn/50WGhh0EAi",
        "Affiliate Link": "https://shorten.asia/uRJv2FqB",
        "Scraping Time": "29-05 Khung: 12:00"
    },
    {
        "Product Name": "Dao Cà Rốt Dao Đồ Chơi Mini Cà Rốt Nhỏ 3d Giúp Thẻ Đẩy Giảm Căng Thẳng Đồ Chơi Quà Tặng Trọng Lực Đồ Chơi Cắt Cà Rốt Hoạt Hình Dễ Thương Món Quà Giáng Sinh Món Quà Sinh Nhật",
        "Current Price": "8.900 ₫",
        "Original Price": "18.000 ₫",
        "Percent Badge": "-51%",
        "Amount Info": "Số lượng: 10",
        "Image": "https://cf.shopee.vn/file/cn-11134207-7r98o-lm8nlriliqeaa6",
        "Original Link": "https://s.shopee.vn/5Apgtzzapl",
        "Affiliate Link": "https://shorten.asia/RzSPpfzm",
        "Scraping Time": "29-05 Khung: 12:00"
    },
    {
        "Product Name": "Sạc dự phòng Energizer Li-polymer 10000mAh/ 3.7V Max 15W, Sạc nhanh PD cho iP/ Samsung, 3 output, Bảo Hành 1 Năm",
        "Current Price": "329.000 ₫",
        "Original Price": "660.000 ₫",
        "Percent Badge": "-50%",
        "Amount Info": "Số lượng: 49",
        "Image": "https://cf.shopee.vn/file/vn-11134207-81ztc-mn183tvl1ywx16",
        "Original Link": "https://s.shopee.vn/4ftQJ51Uqg",
        "Affiliate Link": "https://shorten.asia/wtSSjcvk",
        "Scraping Time": "29-05 Khung: 12:00"
    },
    {
        "Product Name": "PHIÊN BẢN MỚI Chân váy xuông 93cm xẻ tà sau, chân váy xuông dài tôn dáng, thiết kế Dens clothin CV0012",
        "Current Price": "195.895 ₫",
        "Original Price": "390.000 ₫",
        "Percent Badge": "-50%",
        "Amount Info": "Số lượng: 50",
        "Image": "https://cf.shopee.vn/file/vn-11134207-7ras8-mcqercnwgdb0c4",
        "Original Link": "https://s.shopee.vn/4qCqVO0rVj",
        "Affiliate Link": "https://shorten.asia/7KdyYT82",
        "Scraping Time": "29-05 Khung: 12:00"
    },
    {
        "Product Name": "Combo 3 Áo Lá Su Lạnh Đệm Liền Cho Bé Gái (20-57kg), Áo Lót Học Sinh Mặc Chống Hằn Cộm AMYBRA B898",
        "Current Price": "182.000 ₫",
        "Original Price": "366.000 ₫",
        "Percent Badge": "-50%",
        "Amount Info": "Số lượng: 142",
        "Image": "https://cf.shopee.vn/file/vn-11134207-81ztc-mlr6vomp2ps5c0",
        "Original Link": "https://s.shopee.vn/4LGZuT2lWe",
        "Affiliate Link": "https://shorten.asia/Pt7e16eG",
        "Scraping Time": "29-05 Khung: 12:00"
    },
    {
        "Product Name": "Cheerful Mario dép sục cho bé gái hoạt hình bunny & puppy thời trang chống trượt toddler sandals giày sục thoáng khí chống mùi chân cho bé",
        "Current Price": "161.000 ₫",
        "Original Price": "324.000 ₫",
        "Percent Badge": "-50%",
        "Amount Info": "Số lượng: 238",
        "Image": "https://cf.shopee.vn/file/sg-11134201-8260f-mk0pkrmvnj7kb2",
        "Original Link": "https://s.shopee.vn/4Va06m28Bh",
        "Affiliate Link": "https://shorten.asia/Ddr7ezdn",
        "Scraping Time": "29-05 Khung: 12:00"
    },
    {
        "Product Name": "Dép da nam đế cao su đúc nguyên khối - da bò cao cấp ( miễn ship toàn quốc )",
        "Current Price": "99.000 ₫",
        "Original Price": "198.000 ₫",
        "Percent Badge": "-50%",
        "Amount Info": "Số lượng: 55",
        "Image": "https://cf.shopee.vn/file/vn-11134207-7r98o-lwmdwnipehnffb",
        "Original Link": "https://s.shopee.vn/40djVr42Cc",
        "Affiliate Link": "https://shorten.asia/d6dujTER",
        "Scraping Time": "29-05 Khung: 12:00"
    },
    {
        "Product Name": "Thùng 300 - 200 - 100 chiếc Khẩu trang 6D UNI người lớn TUẤN ANH MASK hàng cao cấp chống tia UV và bụi bẩn",
        "Current Price": "91.000 ₫",
        "Original Price": "182.000 ₫",
        "Percent Badge": "-50%",
        "Amount Info": "Số lượng: 2,100",
        "Image": "https://cf.shopee.vn/file/vn-11134201-7ra0g-m7ekwmsizncs1b",
        "Original Link": "https://s.shopee.vn/4Ax9iA3Orf",
        "Affiliate Link": "https://shorten.asia/KDHvhRhr",
        "Scraping Time": "29-05 Khung: 12:00"
    },
    {
        "Product Name": "Áo thun cầu lông nữ Kamito Tshirt Spero V2 chính hãng",
        "Current Price": "90.000 ₫",
        "Original Price": "179.000 ₫",
        "Percent Badge": "-50%",
        "Amount Info": "Số lượng: 10",
        "Image": "https://cf.shopee.vn/file/vn-11134207-81ztc-mmlanvhpngg542",
        "Original Link": "https://s.shopee.vn/3g0t7F5Isa",
        "Affiliate Link": "https://shorten.asia/mt7m7gfG",
        "Scraping Time": "29-05 Khung: 12:00"
    },
    {
        "Product Name": "Bộ Cộc Tay THUN LẠNH MINKYMOM Giáp Năng In Hình Động Vật Cho Bé TN-IN80",
        "Current Price": "75.000 ₫",
        "Original Price": "150.000 ₫",
        "Percent Badge": "-50%",
        "Amount Info": "Số lượng: 154",
        "Image": "https://cf.shopee.vn/file/vn-11134207-81ztc-mmjprc5ygs2767",
        "Original Link": "https://s.shopee.vn/3qKJJY4fXd",
        "Affiliate Link": "https://shorten.asia/ywR469H9",
        "Scraping Time": "29-05 Khung: 12:00"
    },
    {
        "Product Name": "Dầu gội nhuộm tóc tạo bọt, Thuốc nhuộm tóc dạng bọt chiết xuất thiên nhiên | Chenglovehair, Chenglovehairs",
        "Current Price": "75.000 ₫",
        "Original Price": "150.000 ₫",
        "Percent Badge": "-50%",
        "Amount Info": "Số lượng: 280",
        "Image": "https://cf.shopee.vn/file/vn-11134207-81ztc-moqoay59oljj7d",
        "Original Link": "https://s.shopee.vn/3LO2id6ZYY",
        "Affiliate Link": "https://shorten.asia/ptCZn1Fv",
        "Scraping Time": "29-05 Khung: 12:00"
    },
    {
        "Product Name": "Quần short thể thao nữ cạp trễ bản to hottrend . Quần đùi nữ 01 in hình mặc nhà đi chơi đi biển",
        "Current Price": "69.000 ₫",
        "Original Price": "138.000 ₫",
        "Percent Badge": "-50%",
        "Amount Info": "Số lượng: 40",
        "Image": "https://cf.shopee.vn/file/vn-11134207-81ztc-mlptko0fqs5e45",
        "Original Link": "https://s.shopee.vn/3VhSuw5wDb",
        "Affiliate Link": "https://shorten.asia/B7xWzU4A",
        "Scraping Time": "29-05 Khung: 12:00"
    },
    {
        "Product Name": "Đèn P0LICE Cho Xe Máy, Ô Tô, Xe Tải LED Xanh Đỏ Trang Trí Nhiều Chê Độ",
        "Current Price": "52.500 ₫",
        "Original Price": "105.000 ₫",
        "Percent Badge": "-50%",
        "Amount Info": "Số lượng: 10",
        "Image": "https://cf.shopee.vn/file/vn-11134201-7ra0g-m72iuzw74u3r26",
        "Original Link": "https://s.shopee.vn/30lCK17qEW",
        "Affiliate Link": "https://shorten.asia/yntERtE8",
        "Scraping Time": "29-05 Khung: 12:00"
    },
    {
        "Product Name": "Chai thủy tinh 1000ml , chai 1 lít dùng đựng nước DETOX PONGDANG 1000ml",
        "Current Price": "27.000 ₫",
        "Original Price": "54.000 ₫",
        "Percent Badge": "-50%",
        "Amount Info": "Số lượng: 257",
        "Image": "https://cf.shopee.vn/file/vn-11134211-7ras8-m0frm41u59xr9c",
        "Original Link": "https://s.shopee.vn/3B4cWK7CtZ",
        "Affiliate Link": "https://shorten.asia/71766Gwv",
        "Scraping Time": "29-05 Khung: 12:00"
    },
    {
        "Product Name": "Dành Cho IPhone 17 Air 16 15 14 Plus 13 12 11 Pro Max X XR XS Max 7 8 Plus Da Mát Và Dễ Thương Họa Tiết Ngôi Sao Bánh Quy Cặp Đôi Màu Hồng Vỏ Điện Thoại Mềm",
        "Current Price": "23.000 ₫",
        "Original Price": "46.161 ₫",
        "Percent Badge": "-50%",
        "Amount Info": "Số lượng: 9,207",
        "Image": "https://cf.shopee.vn/file/sg-11134201-821fp-mgkcnjfcdwy7b5",
        "Original Link": "https://s.shopee.vn/2g8LvP96uU",
        "Affiliate Link": "https://shorten.asia/CTHa2Pax",
        "Scraping Time": "29-05 Khung: 12:00"
    },
    {
        "Product Name": "Dụng Cụ Gác Bút Hình Mèo Dễ Thương Tiện Lợi",
        "Current Price": "13.900 ₫",
        "Original Price": "28.000 ₫",
        "Percent Badge": "-50%",
        "Amount Info": "Số lượng: 10",
        "Image": "https://cf.shopee.vn/file/921bfc8087f158ce1443d241244968cc",
        "Original Link": "https://s.shopee.vn/2qRm7i8TZX",
        "Affiliate Link": "https://shorten.asia/3fj9pQnu",
        "Scraping Time": "29-05 Khung: 12:00"
    },
    {
        "Product Name": "Miếng Lót Cách Nhiệt , Lót Nồi Xoong Chảo Cốc Bát  ,Làm Từ Gỗ Trúc Tự Nhiên, Sang Trọng",
        "Current Price": "13.000 ₫",
        "Original Price": "26.000 ₫",
        "Percent Badge": "-50%",
        "Amount Info": "Số lượng: 5",
        "Image": "https://cf.shopee.vn/file/vn-11134207-820l4-mizmrjoz6kg0dc",
        "Original Link": "https://s.shopee.vn/2LVVWnANaS",
        "Affiliate Link": "https://shorten.asia/sJExS1hq",
        "Scraping Time": "29-05 Khung: 12:00"
    },
    {
        "Product Name": "Máy Massage Cổ Vai Gáy PHILIPS 3522-mô phỏng massage như các đầu ngón tay",
        "Current Price": "1.780.000 ₫",
        "Original Price": "3.490.000 ₫",
        "Percent Badge": "-49%",
        "Amount Info": "Số lượng: 10",
        "Image": "https://cf.shopee.vn/file/vn-11134207-81ztc-mojhdr0eimf66d",
        "Original Link": "https://s.shopee.vn/2Vovj69kFV",
        "Affiliate Link": "https://shorten.asia/t37J3tmk",
        "Scraping Time": "29-05 Khung: 12:00"
    },
    {
        "Product Name": "UGREEN GaN II Bộ sạc 30W 3 cổng usb-C sạc nhanh Bộ sạc nhanh  kích thước nhỏ cho for iPhone 17-12|Samsung|X515",
        "Current Price": "459.000 ₫",
        "Original Price": "899.000 ₫",
        "Percent Badge": "-49%",
        "Amount Info": "Số lượng: 20",
        "Image": "https://cf.shopee.vn/file/vn-11134207-820l4-mi4cdvixescof3",
        "Original Link": "https://s.shopee.vn/20sf8BBeGQ",
        "Affiliate Link": "https://shorten.asia/1QGV9Nuc",
        "Scraping Time": "29-05 Khung: 12:00"
    },
    {
        "Product Name": "COCODOR Que khuếch tán hoa thật bảo quản / 100ml / 1 lọ / Nhiều Hương / Que hương thơm số 1 Hàn Quốc / mùi hương sang trọng",
        "Current Price": "165.000 ₫",
        "Original Price": "325.000 ₫",
        "Percent Badge": "-49%",
        "Amount Info": "Số lượng: 174",
        "Image": "https://cf.shopee.vn/file/sg-11134207-824ip-mf9coqqhwe1bed",
        "Original Link": "https://s.shopee.vn/2BC5KUB0vT",
        "Affiliate Link": "https://shorten.asia/jWurYU79",
        "Scraping Time": "29-05 Khung: 12:00"
    },
    {
        "Product Name": "Áo thun boxy local brand CLOUDZY 100% cotton 250gsm dày dặn áo phông form rộng nam nữ unisex WARRI",
        "Current Price": "161.991 ₫",
        "Original Price": "318.000 ₫",
        "Percent Badge": "-49%",
        "Amount Info": "Số lượng: 1,110",
        "Image": "https://cf.shopee.vn/file/vn-11134207-81ztc-mlx4ue09ntvnda",
        "Original Link": "https://s.shopee.vn/1gFojZCuwO",
        "Affiliate Link": "https://shorten.asia/j1JfKjJ1",
        "Scraping Time": "29-05 Khung: 12:00"
    },
    {
        "Product Name": "[Tặng kèm Đai] Set váy dài nàng thơ ANNA HOUSE set áo chân váy dài tiểu thư, áo ren kèm váy dáng dài nhẹ nhàng nàng thơ",
        "Current Price": "112.100 ₫",
        "Original Price": "219.000 ₫",
        "Percent Badge": "-49%",
        "Amount Info": "Số lượng: 200",
        "Image": "https://cf.shopee.vn/file/vn-11134207-7ras8-mchop6slo8wye8",
        "Original Link": "https://s.shopee.vn/1qZEvsCHbR",
        "Affiliate Link": "https://shorten.asia/DBtUDPC4",
        "Scraping Time": "29-05 Khung: 12:00"
    },
    {
        "Product Name": "Ugreen 10Gbps USB3.1 2 chiếc 3 chiếc USB-C Nữ sang USB-A Nam Adapter USB-C Nữ sang USB-A Nam Adapter Nhựa",
        "Current Price": "86.000 ₫",
        "Original Price": "169.000 ₫",
        "Percent Badge": "-49%",
        "Amount Info": "Số lượng: 100",
        "Image": "https://cf.shopee.vn/file/cn-11134207-7r98o-lwz2uu8kkyzne1",
        "Original Link": "https://s.shopee.vn/1LcyKxEBcM",
        "Affiliate Link": "https://shorten.asia/WfT7t41K",
        "Scraping Time": "29-05 Khung: 12:00"
    },
    {
        "Product Name": "[199K 5 HỘP] Kích mí WINKISS Có Tay Cầm Dễ Dán Không Cần Dụng Cụ - Miếng Kích Mí Tạo Mí Tự Nhiên, Bám Chắc, Không Lộ Keo",
        "Current Price": "59.000 ₫",
        "Original Price": "115.000 ₫",
        "Percent Badge": "-49%",
        "Amount Info": "Số lượng: 50",
        "Image": "https://cf.shopee.vn/file/vn-11134207-81ztc-mlq3d8l3kxz9e8",
        "Original Link": "https://s.shopee.vn/1VwOXGDYHP",
        "Affiliate Link": "https://shorten.asia/d1CDhxn5",
        "Scraping Time": "29-05 Khung: 12:00"
    },
    {
        "Product Name": "Dây buộc tóc nữ style Hàn Quốc đơn giản, nơ - phù hợp mùa thu đông",
        "Current Price": "39.420 ₫",
        "Original Price": "77.000 ₫",
        "Percent Badge": "-49%",
        "Amount Info": "Số lượng: 20",
        "Image": "https://cf.shopee.vn/file/sg-11134201-8259s-mgg6neno268fa4",
        "Original Link": "https://s.shopee.vn/1107wLFSIK",
        "Affiliate Link": "https://shorten.asia/GZ1SHyAm",
        "Scraping Time": "29-05 Khung: 12:00"
    },
    {
        "Product Name": "Giày chạy bộ nam thể thao PEAK Running Feather Lite Công nghệ đệm đế EVA siêu nhẹ thoáng khí EW2207H",
        "Current Price": "619.000 ₫",
        "Original Price": "1.190.000 ₫",
        "Percent Badge": "-48%",
        "Amount Info": "Số lượng: 52",
        "Image": "https://cf.shopee.vn/file/vn-11134207-7ra0g-m7uhhpdwjc77f9",
        "Original Link": "https://s.shopee.vn/1BJY8eEoxN",
        "Affiliate Link": "https://shorten.asia/9u7NHhza",
        "Scraping Time": "29-05 Khung: 12:00"
    },
    {
        "Product Name": "Vitamin Pentavite Women Multivitamin dạng nhai, thiết kế riêng cho nữ, chứa 14 dưỡng chất, giúp duy trì sức sống cho da",
        "Current Price": "157.000 ₫",
        "Original Price": "300.000 ₫",
        "Percent Badge": "-48%",
        "Amount Info": "Số lượng: 300",
        "Image": "https://cf.shopee.vn/file/vn-11134207-7ras8-mczxefqdxc4t3a",
        "Original Link": "https://s.shopee.vn/gNHXjGiyI",
        "Affiliate Link": "https://shorten.asia/zwmGAjUU",
        "Scraping Time": "29-05 Khung: 12:00"
    },
    {
        "Product Name": "Cây Lau Nhà Tự Vắt Thông Minh MOPScratch, Chổi Lau Nhà 360 Độ Kèm Thùng 2 Ngăn Tách Nước Bẩn Cao Cấp",
        "Current Price": "155.000 ₫",
        "Original Price": "300.000 ₫",
        "Percent Badge": "-48%",
        "Amount Info": "Số lượng: 800",
        "Image": "https://cf.shopee.vn/file/vn-11134207-7r98o-lr491lrxn0rd6a",
        "Original Link": "https://s.shopee.vn/qghk2G5dL",
        "Affiliate Link": "https://shorten.asia/7hhYfZeB",
        "Scraping Time": "29-05 Khung: 12:00"
    },
    {
        "Product Name": "Áo Sơ Mi Kẻ Sọc Tay Dài Nam Nữ Hàn Quốc Local Brand KATHOLIC Chất Liệu Oxford Form Rộng 3 Màu Xám, Hồng, Xanh KAT012",
        "Current Price": "155.000 ₫",
        "Original Price": "300.000 ₫",
        "Percent Badge": "-48%",
        "Amount Info": "Số lượng: 360",
        "Image": "https://cf.shopee.vn/file/vn-11134207-81ztc-mokuqq098ruq69",
        "Original Link": "https://s.shopee.vn/LkR97HzeG",
        "Affiliate Link": "https://shorten.asia/qj6Hrg9S",
        "Scraping Time": "29-05 Khung: 12:00"
    },
    {
        "Product Name": "Thuốc Nhuộm Tóc Màu NÂU ĐEN Không Tẩy | Chenglovehair, Chenglovehairs",
        "Current Price": "104.000 ₫",
        "Original Price": "200.000 ₫",
        "Percent Badge": "-48%",
        "Amount Info": "Số lượng: 60",
        "Image": "https://cf.shopee.vn/file/br-11134201-820ls-mnlc93laqghwa8",
        "Original Link": "https://s.shopee.vn/W3rLQHMJJ",
        "Affiliate Link": "https://shorten.asia/qQWssMdy",
        "Scraping Time": "29-05 Khung: 12:00"
    },
    {
        "Product Name": "AIMO Đèn pin COB zoom siêu sáng, pin dung lượng lớn, chiếu sáng siêu sáng cho ngoài trời và gia đình",
        "Current Price": "83.400 ₫",
        "Original Price": "159.000 ₫",
        "Percent Badge": "-48%",
        "Amount Info": "Số lượng: 50",
        "Image": "https://cf.shopee.vn/file/vn-11134207-81ztc-mkj6k9c9mlmwab",
        "Original Link": "https://s.shopee.vn/17akVJGKE",
        "Affiliate Link": "https://shorten.asia/cPbj6njG",
        "Scraping Time": "29-05 Khung: 12:00"
    },
    {
        "Product Name": "1kg Đậu lăng đỏ (Red Lentils) Canada hữu cơ rất tốt cho sức khoẻ Thiên Thảo Organic",
        "Current Price": "59.999 ₫",
        "Original Price": "115.000 ₫",
        "Percent Badge": "-48%",
        "Amount Info": "Số lượng: 50",
        "Image": "https://cf.shopee.vn/file/sg-11134201-7qvej-ljcjkq3ooef418",
        "Original Link": "https://s.shopee.vn/BR0woIczH",
        "Affiliate Link": "https://shorten.asia/BvTufHHk",
        "Scraping Time": "29-05 Khung: 12:00"
    },
    {
        "Product Name": "Khăn choàng in hình Niche mới Tam giác đỏ Khăn lụa nữ",
        "Current Price": "50.220 ₫",
        "Original Price": "97.000 ₫",
        "Percent Badge": "-48%",
        "Amount Info": "Số lượng: 150",
        "Image": "https://cf.shopee.vn/file/sg-11134201-821dq-mghmj1tfqxos54",
        "Original Link": "https://s.shopee.vn/AUrDFnfI1I",
        "Affiliate Link": "https://shorten.asia/19sYaujK",
        "Scraping Time": "29-05 Khung: 12:00"
    },
    {
        "Product Name": "Chữ Cái Đèn Led, Chữ Led Cao 22CM Trang Trí Có Từ Chữ A-Z Decor Trang Trí Tiệc, Sinh Nhật",
        "Current Price": "39.000 ₫",
        "Original Price": "75.000 ₫",
        "Percent Badge": "-48%",
        "Amount Info": "Số lượng: 10",
        "Image": "https://cf.shopee.vn/file/vn-11134207-7r98o-lubw5qr1mrrz01",
        "Original Link": "https://s.shopee.vn/AKXn3UfvMH",
        "Affiliate Link": "https://shorten.asia/ZBpRA3F8",
        "Scraping Time": "29-05 Khung: 12:00"
    },
    {
        "Product Name": "Kính râm gọng nhỏ cổ điển chống tia cực tím cho nam nữ",
        "Current Price": "35.640 ₫",
        "Original Price": "68.040 ₫",
        "Percent Badge": "-48%",
        "Amount Info": "Số lượng: 65",
        "Image": "https://cf.shopee.vn/file/sg-11134201-7rdvl-mc7c56hgafimfc",
        "Original Link": "https://s.shopee.vn/AAEMrBgYhG",
        "Affiliate Link": "https://shorten.asia/gjcfmy8j",
        "Scraping Time": "29-05 Khung: 12:00"
    },
    {
        "Product Name": "Rèm Cửa Dán Tường, Rèm Cửa Sổ vải gấm cao cấp chống nắng tốt  treo phòng ngủ, giường tầng, dán bếp - ThanhMinhcurtain",
        "Current Price": "33.000 ₫",
        "Original Price": "64.000 ₫",
        "Percent Badge": "-48%",
        "Amount Info": "Số lượng: 2,280",
        "Image": "https://cf.shopee.vn/file/b7b5d3d31fd6f747857f169187da7af7",
        "Original Link": "https://s.shopee.vn/4ftQJ55HGM",
        "Affiliate Link": "https://shorten.asia/ggPqP1Ne",
        "Scraping Time": "29-05 Khung: 12:00"
    },
    {
        "Product Name": "Hoạt Hình Dễ Thương Doremon Chống Thấm Nước Miếng Dán 103 Chiếc Cho Mũ Bảo Hiểm Xe Đạp Tay Tài Khoản Bút Chì Đề Can",
        "Current Price": "25.920 ₫",
        "Original Price": "49.680 ₫",
        "Percent Badge": "-48%",
        "Amount Info": "Số lượng: 10",
        "Image": "https://cf.shopee.vn/file/sg-11134201-7rdw4-mc79e2wp09ji6b",
        "Original Link": "https://s.shopee.vn/4qCqVO4dvP",
        "Affiliate Link": "https://shorten.asia/h2WPctg5",
        "Scraping Time": "29-05 Khung: 12:00"
    },
    {
        "Product Name": "Trend Brand Dễ Thương Ngôi Sao Xanh Lá Khâu Dây Treo Hoạt Hình Dễ Thương Ngôi Sao Vòng Tay Dây Buộc",
        "Current Price": "20.899 ₫",
        "Original Price": "39.998 ₫",
        "Percent Badge": "-48%",
        "Amount Info": "Số lượng: 50",
        "Image": "https://cf.shopee.vn/file/sg-11134201-824ji-mdx2xaw264u836",
        "Original Link": "https://s.shopee.vn/4LGZuT6XwK",
        "Affiliate Link": "https://shorten.asia/3EwgDGQZ",
        "Scraping Time": "29-05 Khung: 12:00"
    },
    {
        "Product Name": "Nệm Lò Xo Độc Lập Với 3 Tầng Foam Hỗ Trợ 25cm - 10in Euro Top OPP Pocket Spring Mattress",
        "Current Price": "3.763.000 ₫",
        "Original Price": "7.100.000 ₫",
        "Percent Badge": "-47%",
        "Amount Info": "Số lượng: 6",
        "Image": "https://cf.shopee.vn/file/vn-11134207-820l4-mfdltkfhr0gfa8",
        "Original Link": "https://s.shopee.vn/4Va06m5ubN",
        "Affiliate Link": "https://shorten.asia/smKBuxQF",
        "Scraping Time": "29-05 Khung: 12:00"
    },
    {
        "Product Name": "Kem nền UODO che khuyết điểm cao Lâu trôi kiềm dầu Mịn như nhung không mốc 24h 30g",
        "Current Price": "250.000 ₫",
        "Original Price": "470.000 ₫",
        "Percent Badge": "-47%",
        "Amount Info": "Số lượng: 1,200",
        "Image": "https://cf.shopee.vn/file/cn-11134207-820l4-ml8v67rwufwh83",
        "Original Link": "https://s.shopee.vn/40djVr7ocI",
        "Affiliate Link": "https://shorten.asia/3fJDgKVT",
        "Scraping Time": "29-05 Khung: 12:00"
    },
    {
        "Product Name": "Son lì lâu trôi, mịn, che phủ viền môi, giúp môi mềm mại, tự nhiên chính hãng Mistine Pretty Me Semi Matte Lipstick 3.5g",
        "Current Price": "206.000 ₫",
        "Original Price": "388.000 ₫",
        "Percent Badge": "-47%",
        "Amount Info": "Số lượng: 270",
        "Image": "https://cf.shopee.vn/file/sg-11134201-820nr-mnts3g1cbbpk0b",
        "Original Link": "https://s.shopee.vn/4Ax9iA7BHL",
        "Affiliate Link": "https://shorten.asia/ve1TQXrK",
        "Scraping Time": "29-05 Khung: 12:00"
    },
    {
        "Product Name": "(PREMIUM) Quần jeans ống rộng eo cao vibe thu đông MINI04",
        "Current Price": "189.999 ₫",
        "Original Price": "359.000 ₫",
        "Percent Badge": "-47%",
        "Amount Info": "Số lượng: 60",
        "Image": "https://cf.shopee.vn/file/vn-11134207-820l4-mfhvxmyfo3rjd4",
        "Original Link": "https://s.shopee.vn/3g0t7F95IG",
        "Affiliate Link": "https://shorten.asia/fTRjg2rB",
        "Scraping Time": "29-05 Khung: 12:00"
    },
    {
        "Product Name": "Xiaozhainv Áo Thun Tay Ngắn Cổ Tròn Chất Cotton Hoạ Tiết In Thời Trang Mùa Hè Cho Phái",
        "Current Price": "138.000 ₫",
        "Original Price": "260.000 ₫",
        "Percent Badge": "-47%",
        "Amount Info": "Số lượng: 200",
        "Image": "https://cf.shopee.vn/file/cn-11134207-820l4-mekuafamabr5a3",
        "Original Link": "https://s.shopee.vn/3qKJJY8RxJ",
        "Affiliate Link": "https://shorten.asia/YSm1BnYM",
        "Scraping Time": "29-05 Khung: 12:00"
    },
    {
        "Product Name": "(Nội Địa Nhật) Chip Chắn Sóng Điện Từ Hitoki - Mèo Thần Tài",
        "Current Price": "128.000 ₫",
        "Original Price": "240.000 ₫",
        "Percent Badge": "-47%",
        "Amount Info": "Số lượng: 30",
        "Image": "https://cf.shopee.vn/file/vn-11134207-7r98o-lzyly4f8vrkdae",
        "Original Link": "https://s.shopee.vn/3LO2idALyE",
        "Affiliate Link": "https://shorten.asia/XEVWP2ed",
        "Scraping Time": "29-05 Khung: 12:00"
    },
    {
        "Product Name": "LANBENA Mặt Nạ Chân (40g) -Dưỡng Da Chân Lột Chân  Tẩy Da Chết Chân Spa Ủ Chân Tẩy Da Chết để loại bỏ vết chai Foot Care",
        "Current Price": "79.000 ₫",
        "Original Price": "150.000 ₫",
        "Percent Badge": "-47%",
        "Amount Info": "Số lượng: 50",
        "Image": "https://cf.shopee.vn/file/vn-11134207-7ras8-mav55m40qfghdc",
        "Original Link": "https://s.shopee.vn/3VhSuw9idH",
        "Affiliate Link": "https://shorten.asia/HBrnDj2Y",
        "Scraping Time": "29-05 Khung: 12:00"
    },
    {
        "Product Name": "Túi Nước Giặt Xả BOOSTER Đậm Đặc Cao Cấp Giặt Sạch Và Lưu Hương Trên Từng Sợi Vải.",
        "Current Price": "69.000 ₫",
        "Original Price": "130.000 ₫",
        "Percent Badge": "-47%",
        "Amount Info": "Số lượng: 360",
        "Image": "https://cf.shopee.vn/file/vn-11134207-7ra0g-m8hfpvbn4oxw2b",
        "Original Link": "https://s.shopee.vn/30lCK1BceC",
        "Affiliate Link": "https://shorten.asia/KNMx3fJ3",
        "Scraping Time": "29-05 Khung: 12:00"
    },
    {
        "Product Name": "NiLANK Remote Điều khiển điều hòa SHARP có nút ECO tiết kiệm điện model AH-AP9SMD2",
        "Current Price": "64.000 ₫",
        "Original Price": "120.000 ₫",
        "Percent Badge": "-47%",
        "Amount Info": "Số lượng: 50",
        "Image": "https://cf.shopee.vn/file/sg-11134201-82607-mlzrg7angf7m08",
        "Original Link": "https://s.shopee.vn/3B4cWKAzJF",
        "Affiliate Link": "https://shorten.asia/dMc9n2sk",
        "Scraping Time": "29-05 Khung: 12:00"
    },
    {
        "Product Name": "Thắt Lưng Nữ Phong Cách Retro Độc Đáo, Chất Liệu Da Nâu",
        "Current Price": "59.600 ₫",
        "Original Price": "112.000 ₫",
        "Percent Badge": "-47%",
        "Amount Info": "Số lượng: 51",
        "Image": "https://cf.shopee.vn/file/sg-11134201-824g8-mfktusn4n6dl30",
        "Original Link": "https://s.shopee.vn/2g8LvPCtKA",
        "Affiliate Link": "https://shorten.asia/q1bR7bdB",
        "Scraping Time": "29-05 Khung: 12:00"
    },
    {
        "Product Name": "UNMEGONI Nhãn dán nghệ thuật làm móng tay kiểu Pháp, Đầu dải trắng Dải làm móng tay kiểu Pháp, Mẫu trang trí DIY chuyên nghiệp Fringe Nhãn dán móng tay nghệ thuật tự dính Dụng cụ làm móng tay",
        "Current Price": "31.900 ₫",
        "Original Price": "60.280 ₫",
        "Percent Badge": "-47%",
        "Amount Info": "Số lượng: 60",
        "Image": "https://cf.shopee.vn/file/sg-11134201-825zn-mli2ui199xqc85",
        "Original Link": "https://s.shopee.vn/2qRm7iCFzD",
        "Affiliate Link": "https://shorten.asia/e5bd7zYp",
        "Scraping Time": "29-05 Khung: 12:00"
    },
    {
        "Product Name": "Hai lựa chọn: 1. Bản cơ bản 300Mbps, 1 băng tần, USB không dây không cần cài driver, 2.4GHz, tích hợp Bluetooth và WiFi; 2. USB không dây 2 băng tần AC600, hỗ trợ 5G+2.4G, tự động nhận diện trên Windows 7/8/10/11, tích hợp Bluetooth và WiFi.",
        "Current Price": "31.900 ₫",
        "Original Price": "60.500 ₫",
        "Percent Badge": "-47%",
        "Amount Info": "Số lượng: 20",
        "Image": "https://cf.shopee.vn/file/sg-11134301-82635-mjgrrb19twqp04",
        "Original Link": "https://s.shopee.vn/2LVVWnEA08",
        "Affiliate Link": "https://shorten.asia/MhbvRc6x",
        "Scraping Time": "29-05 Khung: 12:00"
    },
    {
        "Product Name": "Ổ Cắm Chuyển Đổi Du Lịch Deli, Ổ Điện Du Lịch Nhỏ Gọn Du Lịch Tiêu Chuẩn Mỹ, Anh, Châu Âu, Nhật",
        "Current Price": "31.000 ₫",
        "Original Price": "59.000 ₫",
        "Percent Badge": "-47%",
        "Amount Info": "Số lượng: 10",
        "Image": "https://cf.shopee.vn/file/vn-11134207-81ztc-mo5ansjmkef955",
        "Original Link": "https://s.shopee.vn/2Vovj6DWfB",
        "Affiliate Link": "https://shorten.asia/jGMPPrvh",
        "Scraping Time": "29-05 Khung: 12:00"
    },
    {
        "Product Name": "Nấm Sapa sấy khô ăn chay ăn kiêng loại 1 túi 100gr Thiên Thảo Organic",
        "Current Price": "29.400 ₫",
        "Original Price": "55.000 ₫",
        "Percent Badge": "-47%",
        "Amount Info": "Số lượng: 100",
        "Image": "https://cf.shopee.vn/file/vn-11134211-7r98o-lln4ob9roou4f5",
        "Original Link": "https://s.shopee.vn/20sf8BFQg6",
        "Affiliate Link": "https://shorten.asia/yfwScHd8",
        "Scraping Time": "29-05 Khung: 12:00"
    },
    {
        "Product Name": "Sách: 10 Vạn Câu Hỏi Vì Sao (Bản Nhỏ)",
        "Current Price": "29.000 ₫",
        "Original Price": "55.000 ₫",
        "Percent Badge": "-47%",
        "Amount Info": "Số lượng: 10",
        "Image": "https://cf.shopee.vn/file/vn-11134207-7ras8-mcj06xklk97x84",
        "Original Link": "https://s.shopee.vn/2BC5KUEnL9",
        "Affiliate Link": "https://shorten.asia/zdqMzm63",
        "Scraping Time": "29-05 Khung: 12:00"
    },
    {
        "Product Name": "Đai Nịt Bụng Thông Hơi Chống Cuộn thế hệ mới",
        "Current Price": "28.900 ₫",
        "Original Price": "55.000 ₫",
        "Percent Badge": "-47%",
        "Amount Info": "Số lượng: 50",
        "Image": "https://cf.shopee.vn/file/41f459784fffcaf9d44d98940f30394d",
        "Original Link": "https://s.shopee.vn/1gFojZGhM4",
        "Affiliate Link": "https://shorten.asia/rRcrg3fp",
        "Scraping Time": "29-05 Khung: 12:00"
    },
    {
        "Product Name": "Ren Tam Giác Đầu Nữ Pháp Vintage Dệt Kim Bandana Thời Trang Đa Năng Phụ Kiện Tóc",
        "Current Price": "26.340 ₫",
        "Original Price": "49.728 ₫",
        "Percent Badge": "-47%",
        "Amount Info": "Số lượng: 160",
        "Image": "https://cf.shopee.vn/file/sg-11134201-7rdvw-lxgomfslg2143a",
        "Original Link": "https://s.shopee.vn/1qZEvsG417",
        "Affiliate Link": "https://shorten.asia/21fZekhh",
        "Scraping Time": "29-05 Khung: 12:00"
    },
    {
        "Product Name": "Hạt giống Rau Củ Quả trồng chậu, rau ăn lá,dây leo trồng quanh năm,nảy mầm tốt - Hạt giống Rạng Đông",
        "Current Price": "15.900 ₫",
        "Original Price": "29.833 ₫",
        "Percent Badge": "-47%",
        "Amount Info": "Số lượng: 450",
        "Image": "https://cf.shopee.vn/file/vn-11134207-23010-cll1r5cv44lv49",
        "Original Link": "https://s.shopee.vn/1LcyKxHy22",
        "Affiliate Link": "https://shorten.asia/4G7AYMkw",
        "Scraping Time": "29-05 Khung: 12:00"
    },
    {
        "Product Name": "Dao gọt hoa quả có nắp đậy an toàn tiện dụng",
        "Current Price": "9.000 ₫",
        "Original Price": "17.000 ₫",
        "Percent Badge": "-47%",
        "Amount Info": "Số lượng: 5",
        "Image": "https://cf.shopee.vn/file/vn-11134207-7r98o-lyc1dlnsbdjhae",
        "Original Link": "https://s.shopee.vn/1VwOXGHKh5",
        "Affiliate Link": "https://shorten.asia/dy4N77nB",
        "Scraping Time": "29-05 Khung: 12:00"
    },
    {
        "Product Name": "Túi màng bọc thực phẩm JYoohome chất liệu PE co dãn có chun siêu dai, Túi gấu bọc đồ ăn",
        "Current Price": "7.900 ₫",
        "Original Price": "15.000 ₫",
        "Percent Badge": "-47%",
        "Amount Info": "Số lượng: 100",
        "Image": "https://cf.shopee.vn/file/vn-11134207-7r98o-lusqvfd3s8pxca",
        "Original Link": "https://s.shopee.vn/1107wLJEi0",
        "Affiliate Link": "https://shorten.asia/fKCVH6RR",
        "Scraping Time": "29-05 Khung: 12:00"
    },
    {
        "Product Name": "Máy chiếu Mini di động GOOJODOQ Android 11 Xoay miễn phí 270 ° Bluetooth 5.0 Màn hình lớn",
        "Current Price": "1.500.000 ₫",
        "Original Price": "2.780.000 ₫",
        "Percent Badge": "-46%",
        "Amount Info": "Số lượng: 27",
        "Image": "https://cf.shopee.vn/file/vn-11134207-7ra0g-m6xv9lqy682vbf",
        "Original Link": "https://s.shopee.vn/1BJY8eIbN3",
        "Affiliate Link": "https://shorten.asia/uBFv2vdp",
        "Scraping Time": "29-05 Khung: 12:00"
    }
]